[
  {
    "id": "dedust_1782829141",
    "data": {
      "id": "dedust_1782829141",
      "fee": 0.160773,
      "pnl": 0.476333,
      "side": "buy",
      "amount": 17876.83189,
      "reason": "take_profit",
      "status": "closed",
      "symbol": "GRINCH/USDT",
      "outcome": "win",
      "pnl_pct": 10.25,
      "exit_rsi": null,
      "closed_at": "2026-07-01T11:21:57.756569",
      "entry_rsi": 0.0,
      "in_profit": true,
      "opened_at": "2026-06-30T14:19:01.956149",
      "stake_ton": 4.6465,
      "stop_loss": 0.00048831,
      "trail_pct": 7.0,
      "exit_price": 0.00047495,
      "high_water": 0.00049423,
      "entry_price": 0.00042439,
      "exit_regime": "SQUEEZE",
      "net_pct_now": 10.43,
      "net_ton_now": 0.495426,
      "take_profit": 0.0005547,
      "close_reason": "take_profit",
      "duration_min": 1262.9,
      "entry_regime": "SQUEEZE",
      "exit_anomaly": false,
      "exit_atr_pct": 0.517,
      "ai_confidence": 92.0,
      "entry_anomaly": false,
      "entry_atr_pct": 0.484,
      "min_gross_pct": 30.7,
      "value_ton_now": 5.553461,
      "entry_bo_score": 40.2,
      "entry_sm_label": "",
      "entry_sm_score": 0.0,
      "exit_ai_signal": "BUY",
      "breakeven_price": 0.00046152,
      "entry_bo_signal": "COILING",
      "entry_mom_score": 35.0,
      "entry_price_ton": 0.0002574623064873669,
      "entry_mom_signal": "BUILDING",
      "entry_sm_buys_1h": 0,
      "entry_sm_sells_1h": 0,
      "exit_ai_confidence": 89.2
    },
    "closed_at": "2026-07-01T11:21:57.756569"
  },
  {
    "id": "dedust_1782903318",
    "data": {
      "id": "dedust_1782903318",
      "fee": 2.493091,
      "pnl": 1.895282,
      "side": "buy",
      "amount": 268195.407081,
      "reason": "take_profit",
      "status": "closed",
      "symbol": "GRINCH/USDT",
      "outcome": "win",
      "pnl_pct": 2.38,
      "exit_rsi": null,
      "closed_at": "2026-07-01T11:22:13.614792",
      "entry_rsi": 0.0,
      "in_profit": true,
      "opened_at": "2026-07-01T10:55:18.133976",
      "stake_ton": 79.728,
      "stop_loss": 0.00048916,
      "trail_pct": 7.0,
      "exit_price": 0.00047495,
      "high_water": 0.00049423,
      "entry_price": 0.00045463,
      "exit_regime": "SQUEEZE",
      "net_pct_now": 3.0,
      "net_ton_now": 2.3981,
      "take_profit": 0.00055882,
      "close_reason": "take_profit",
      "duration_min": 26.9,
      "entry_regime": "DOWNTREND",
      "exit_anomaly": false,
      "exit_atr_pct": 0.517,
      "ai_confidence": 90.6,
      "entry_anomaly": false,
      "entry_atr_pct": 0.501,
      "min_gross_pct": 22.9,
      "value_ton_now": 83.315252,
      "entry_bo_score": 35.6,
      "entry_sm_label": "",
      "entry_sm_score": 0.0,
      "exit_ai_signal": "BUY",
      "breakeven_price": 0.00046127,
      "entry_bo_signal": "COILING",
      "entry_mom_score": 41.0,
      "entry_price_ton": 0.0002921292220102023,
      "entry_mom_signal": "BUILDING",
      "entry_sm_buys_1h": 0,
      "entry_sm_sells_1h": 0,
      "exit_ai_confidence": 89.2
    },
    "closed_at": "2026-07-01T11:22:13.614792"
  },
  {
    "id": "dedust_1782903360",
    "data": {
      "id": "dedust_1782903360",
      "fee": 2.307965,
      "pnl": 2.990828,
      "side": "buy",
      "amount": 250310.711721,
      "reason": "take_profit",
      "status": "closed",
      "symbol": "GRINCH/USDT",
      "outcome": "win",
      "pnl_pct": 3.96,
      "exit_rsi": null,
      "closed_at": "2026-07-01T11:22:29.659492",
      "entry_rsi": 0.0,
      "in_profit": true,
      "opened_at": "2026-07-01T10:56:01.093240",
      "stake_ton": 75.504,
      "stop_loss": 0.00048116,
      "trail_pct": 7.0,
      "exit_price": 0.00047495,
      "high_water": 0.00049423,
      "entry_price": 0.00044709,
      "exit_regime": "SQUEEZE",
      "net_pct_now": 1.48,
      "net_ton_now": 1.121755,
      "take_profit": 0.00054968,
      "close_reason": "take_profit",
      "duration_min": 26.5,
      "entry_regime": "DOWNTREND",
      "exit_anomaly": false,
      "exit_atr_pct": 0.517,
      "ai_confidence": 85.8,
      "entry_anomaly": false,
      "entry_atr_pct": 0.44,
      "min_gross_pct": 22.9,
      "value_ton_now": 77.759348,
      "entry_bo_score": 23.0,
      "entry_sm_label": "",
      "entry_sm_score": 0.0,
      "exit_ai_signal": "BUY",
      "breakeven_price": 0.00045374,
      "entry_bo_signal": "COILING",
      "entry_mom_score": 30.8,
      "entry_price_ton": 0.0002937,
      "entry_mom_signal": "BUILDING",
      "entry_sm_buys_1h": 0,
      "entry_sm_sells_1h": 0,
      "exit_ai_confidence": 89.2
    },
    "closed_at": "2026-07-01T11:22:29.659492"
  },
  {
    "id": "dedust_1782903405",
    "data": {
      "id": "dedust_1782903405",
      "fee": 2.331551,
      "pnl": 0.795028,
      "side": "buy",
      "amount": 250238.885591,
      "reason": "take_profit",
      "status": "closed",
      "symbol": "GRINCH/USDT",
      "outcome": "win",
      "pnl_pct": 1.04,
      "exit_rsi": null,
      "closed_at": "2026-07-01T12:24:54.117949",
      "entry_rsi": 0.0,
      "in_profit": false,
      "opened_at": "2026-07-01T10:56:45.946962",
      "stake_ton": 76.56,
      "stop_loss": 0.00049369,
      "trail_pct": 7.0,
      "exit_price": 0.00047297,
      "high_water": 0.00050251,
      "entry_price": 0.00045876,
      "exit_regime": "TRANSITION",
      "net_pct_now": -0.86,
      "net_ton_now": -0.662489,
      "take_profit": 0.00056399,
      "close_reason": "take_profit",
      "duration_min": 88.1,
      "entry_regime": "VOLATILE",
      "exit_anomaly": false,
      "exit_atr_pct": 0.534,
      "ai_confidence": 87.0,
      "entry_anomaly": true,
      "entry_atr_pct": 0.451,
      "min_gross_pct": 12.7,
      "value_ton_now": 77.023748,
      "entry_bo_score": 38.5,
      "entry_sm_label": "",
      "entry_sm_score": 0.0,
      "exit_ai_signal": "BUY",
      "breakeven_price": 0.00046555,
      "entry_bo_signal": "COILING",
      "entry_mom_score": 34.8,
      "entry_price_ton": 0.00030508055144677583,
      "entry_mom_signal": "BUILDING",
      "entry_sm_buys_1h": 0,
      "entry_sm_sells_1h": 0,
      "exit_ai_confidence": 88.7
    },
    "closed_at": "2026-07-01T12:24:54.117949"
  },
  {
    "id": "dedust_1782902834",
    "data": {
      "id": "dedust_1782902834",
      "fee": 0.793387,
      "pnl": 2.090742,
      "side": "buy",
      "amount": 80167.660939,
      "reason": "take_profit",
      "status": "closed",
      "symbol": "GRINCH/USDT",
      "outcome": "win",
      "pnl_pct": 8.6,
      "exit_rsi": null,
      "closed_at": "2026-07-01T13:50:38.426653",
      "entry_rsi": 0.0,
      "in_profit": false,
      "opened_at": "2026-07-01T10:47:14.665301",
      "stake_ton": 24.318,
      "stop_loss": 0.00053435,
      "trail_pct": 7.0,
      "exit_price": 0.00051999,
      "high_water": 0.00054114,
      "entry_price": 0.00046967,
      "exit_regime": "SQUEEZE",
      "net_pct_now": -1.0,
      "net_ton_now": -0.24508,
      "take_profit": 0.00058709,
      "close_reason": "take_profit",
      "duration_min": 183.4,
      "entry_regime": "RANGING",
      "exit_anomaly": false,
      "exit_atr_pct": 0.511,
      "ai_confidence": 77.2,
      "entry_anomaly": false,
      "entry_atr_pct": 0.456,
      "min_gross_pct": 13.8,
      "value_ton_now": 24.675676,
      "entry_bo_score": 16.0,
      "entry_sm_label": "",
      "entry_sm_score": 0.0,
      "exit_ai_signal": "BUY",
      "breakeven_price": 0.00048136,
      "entry_bo_signal": "FLAT",
      "entry_mom_score": 32.3,
      "entry_price_ton": 0.00030101807539448553,
      "entry_mom_signal": "BUILDING",
      "entry_sm_buys_1h": 0,
      "entry_sm_sells_1h": 0,
      "exit_ai_confidence": 91.3
    },
    "closed_at": "2026-07-01T13:50:38.426653"
  },
  {
    "id": "dedust_1782903613",
    "data": {
      "id": "dedust_1782903613",
      "fee": 1.871413,
      "pnl": 5.038062,
      "side": "buy",
      "amount": 189255.322945,
      "reason": "take_profit",
      "status": "closed",
      "symbol": "GRINCH/USDT",
      "outcome": "win",
      "pnl_pct": 8.59,
      "exit_rsi": null,
      "closed_at": "2026-07-01T13:50:55.095757",
      "entry_rsi": 0.0,
      "in_profit": false,
      "opened_at": "2026-07-01T11:00:13.982634",
      "stake_ton": 58.632,
      "stop_loss": 0.00052918,
      "trail_pct": 7.0,
      "exit_price": 0.00051999,
      "high_water": 0.00054114,
      "entry_price": 0.00046884,
      "exit_regime": "SQUEEZE",
      "net_pct_now": -2.24,
      "net_ton_now": -1.317575,
      "take_profit": 0.0005771,
      "close_reason": "take_profit",
      "duration_min": 170.7,
      "entry_regime": "DOWNTREND",
      "exit_anomaly": false,
      "exit_atr_pct": 0.511,
      "ai_confidence": 69.8,
      "entry_anomaly": false,
      "entry_atr_pct": 0.454,
      "min_gross_pct": 12.9,
      "value_ton_now": 58.252954,
      "entry_bo_score": 14.7,
      "entry_sm_label": "",
      "entry_sm_score": 0.0,
      "exit_ai_signal": "BUY",
      "breakeven_price": 0.00047645,
      "entry_bo_signal": "FLAT",
      "entry_mom_score": 32.3,
      "entry_price_ton": 0.00030508055144677583,
      "entry_mom_signal": "BUILDING",
      "entry_sm_buys_1h": 0,
      "entry_sm_sells_1h": 0,
      "exit_ai_confidence": 91.3
    },
    "closed_at": "2026-07-01T13:50:55.095757"
  },
  {
    "id": "dedust_1782768933",
    "data": {
      "id": "dedust_1782768933",
      "fee": 0.15113,
      "pnl": 0.770151,
      "side": "buy",
      "amount": 14956.23112,
      "reason": "take_profit",
      "status": "closed",
      "symbol": "GRINCH/USDT",
      "outcome": "win",
      "pnl_pct": 17.69,
      "exit_rsi": null,
      "closed_at": "2026-07-01T13:54:48.569473",
      "entry_rsi": 0.0,
      "in_profit": false,
      "opened_at": "2026-06-29T21:35:33.485868",
      "stake_ton": 4.3548,
      "stop_loss": 0.00055609,
      "trail_pct": 7.0,
      "exit_price": 0.0005502,
      "high_water": 0.00055931,
      "entry_price": 0.00046028,
      "exit_regime": "RANGING",
      "net_pct_now": -3.44,
      "net_ton_now": -0.153294,
      "take_profit": 0.00060416,
      "close_reason": "take_profit",
      "duration_min": 2419.3,
      "entry_regime": "RANGING",
      "exit_anomaly": false,
      "exit_atr_pct": 0.554,
      "ai_confidence": 89.3,
      "entry_anomaly": false,
      "entry_atr_pct": 0.516,
      "min_gross_pct": 20.8,
      "value_ton_now": 4.603541,
      "entry_bo_score": 44.1,
      "entry_sm_label": "",
      "entry_sm_score": 0.0,
      "exit_ai_signal": "BUY",
      "breakeven_price": 0.00050294,
      "entry_bo_signal": "PRIMED",
      "entry_mom_score": 43.1,
      "entry_mom_signal": "BUILDING",
      "entry_sm_buys_1h": 0,
      "entry_sm_sells_1h": 0,
      "exit_ai_confidence": 82.4
    },
    "closed_at": "2026-07-01T13:54:48.569473"
  },
  {
    "id": "dedust_1782884218",
    "data": {
      "id": "dedust_1782884218",
      "fee": 0.207087,
      "pnl": 0.949391,
      "side": "buy",
      "amount": 20344.711802,
      "reason": "take_profit",
      "status": "closed",
      "symbol": "GRINCH/USDT",
      "outcome": "win",
      "pnl_pct": 15.41,
      "exit_rsi": null,
      "closed_at": "2026-07-01T13:55:04.474799",
      "entry_rsi": 0.0,
      "in_profit": false,
      "opened_at": "2026-07-01T05:36:58.399500",
      "stake_ton": 6.1628,
      "stop_loss": 0.00055327,
      "trail_pct": 7.0,
      "exit_price": 0.0005502,
      "high_water": 0.00055931,
      "entry_price": 0.00046769,
      "exit_regime": "RANGING",
      "net_pct_now": -5.1,
      "net_ton_now": -0.319301,
      "take_profit": 0.00060178,
      "close_reason": "take_profit",
      "duration_min": 498.1,
      "entry_regime": "RANGING",
      "exit_anomaly": false,
      "exit_atr_pct": 0.554,
      "ai_confidence": 87.5,
      "entry_anomaly": false,
      "entry_atr_pct": 0.509,
      "min_gross_pct": 18.3,
      "value_ton_now": 6.26212,
      "entry_bo_score": 16.8,
      "entry_sm_label": "",
      "entry_sm_score": 0.0,
      "exit_ai_signal": "BUY",
      "breakeven_price": 0.0004997,
      "entry_bo_signal": "FLAT",
      "entry_mom_score": 26.4,
      "entry_price_ton": 0.00030009403232926653,
      "entry_mom_signal": "CALM",
      "entry_sm_buys_1h": 0,
      "entry_sm_sells_1h": 0,
      "exit_ai_confidence": 82.4
    },
    "closed_at": "2026-07-01T13:55:04.474799"
  },
  {
    "id": "dedust_1782903667",
    "data": {
      "id": "dedust_1782903667",
      "fee": 1.303555,
      "pnl": 4.880178,
      "side": "buy",
      "amount": 126520.626488,
      "reason": "take_profit",
      "status": "closed",
      "symbol": "GRINCH/USDT",
      "outcome": "win",
      "pnl_pct": 12.34,
      "exit_rsi": null,
      "closed_at": "2026-07-01T13:55:20.648144",
      "entry_rsi": 0.0,
      "in_profit": false,
      "opened_at": "2026-07-01T11:01:07.519515",
      "stake_ton": 39.5528,
      "stop_loss": 0.0005526,
      "trail_pct": 7.0,
      "exit_price": 0.0005502,
      "high_water": 0.00055931,
      "entry_price": 0.00048011,
      "exit_regime": "RANGING",
      "net_pct_now": -3.42,
      "net_ton_now": -1.355072,
      "take_profit": 0.00059249,
      "close_reason": "take_profit",
      "duration_min": 174.2,
      "entry_regime": "UPTREND",
      "exit_anomaly": false,
      "exit_atr_pct": 0.554,
      "ai_confidence": 93.3,
      "entry_anomaly": false,
      "entry_atr_pct": 0.529,
      "min_gross_pct": 13.2,
      "value_ton_now": 38.94316,
      "entry_bo_score": 31.0,
      "entry_sm_label": "",
      "entry_sm_score": 0.0,
      "exit_ai_signal": "BUY",
      "breakeven_price": 0.00048932,
      "entry_bo_signal": "COILING",
      "entry_mom_score": 33.5,
      "entry_price_ton": 0.0003106513009429925,
      "entry_mom_signal": "BUILDING",
      "entry_sm_buys_1h": 0,
      "entry_sm_sells_1h": 0,
      "exit_ai_confidence": 82.4
    },
    "closed_at": "2026-07-01T13:55:20.648144"
  },
  {
    "id": "dedust_1782908774",
    "data": {
      "id": "dedust_1782908774",
      "fee": 4.471176,
      "pnl": 15.963446,
      "side": "buy",
      "amount": 432871.787774,
      "reason": "take_profit",
      "status": "closed",
      "symbol": "GRINCH/USDT",
      "outcome": "win",
      "pnl_pct": 11.63,
      "exit_rsi": null,
      "closed_at": "2026-07-01T13:55:35.925396",
      "entry_rsi": 0.0,
      "opened_at": "2026-07-01T12:26:14.834161",
      "stake_ton": 137.25,
      "stop_loss": 0.0005526,
      "trail_pct": 7.0,
      "exit_price": 0.0005502,
      "high_water": 0.00055931,
      "entry_price": 0.00048271,
      "exit_regime": "RANGING",
      "take_profit": 0.00054308,
      "close_reason": "take_profit",
      "duration_min": 89.4,
      "entry_regime": "UPTREND",
      "exit_anomaly": false,
      "exit_atr_pct": 0.554,
      "ai_confidence": 91.5,
      "entry_anomaly": false,
      "entry_atr_pct": 0.506,
      "min_gross_pct": 12.5,
      "entry_bo_score": 16.1,
      "entry_sm_label": "",
      "entry_sm_score": 0.0,
      "exit_ai_signal": "BUY",
      "breakeven_price": 0.00048885,
      "entry_bo_signal": "FLAT",
      "entry_mom_score": 20.5,
      "entry_price_ton": 0.000317885685524018,
      "entry_mom_signal": "CALM",
      "entry_sm_buys_1h": 0,
      "entry_sm_sells_1h": 0,
      "exit_ai_confidence": 82.4
    },
    "closed_at": "2026-07-01T13:55:35.925396"
  }
]