[
  {
    "trade_id": "dedust_1782909191",
    "data": {
      "id": "dedust_1782909191",
      "pnl": 0.0,
      "side": "buy",
      "amount": 57823.343617,
      "status": "open",
      "symbol": "GRINCH/USDT",
      "entry_rsi": 0.0,
      "in_profit": false,
      "opened_at": "2026-07-01T12:33:11.361645",
      "stake_ton": 18.5963,
      "stop_loss": 0.0,
      "trail_pct": 7.0,
      "high_water": 0.00049041,
      "entry_price": 0.00049041,
      "net_pct_now": -12.66,
      "net_ton_now": -2.368071,
      "take_profit": 0.00056026,
      "entry_regime": "VOLATILE",
      "ai_confidence": 84.7,
      "entry_anomaly": false,
      "entry_atr_pct": 0.495,
      "min_gross_pct": 24.5,
      "value_ton_now": 16.751747,
      "entry_bo_score": 10.7,
      "entry_sm_label": "",
      "entry_sm_score": 0.0,
      "breakeven_price": 0.00050485,
      "entry_bo_signal": "FLAT",
      "entry_mom_score": 25.3,
      "entry_price_ton": 0.000317,
      "entry_mom_signal": "CALM",
      "entry_sm_buys_1h": 0,
      "entry_sm_sells_1h": 0
    },
    "updated_at": "2026-07-01T15:57:46.334819"
  },
  {
    "trade_id": "dedust_1782913871",
    "data": {
      "id": "dedust_1782913871",
      "pnl": 0.0,
      "side": "buy",
      "amount": 264114.59149,
      "status": "open",
      "symbol": "GRINCH/USDT",
      "entry_rsi": 0.0,
      "in_profit": false,
      "opened_at": "2026-07-01T13:51:11.108410",
      "stake_ton": 92.2284,
      "stop_loss": 0.0,
      "trail_pct": 7.0,
      "high_water": 0.00051999,
      "entry_price": 0.00051999,
      "net_pct_now": -18.23,
      "net_ton_now": -16.834077,
      "take_profit": 0.00058571,
      "entry_regime": "SQUEEZE",
      "ai_confidence": 91.3,
      "entry_anomaly": false,
      "entry_atr_pct": 0.511,
      "min_gross_pct": 22.9,
      "value_ton_now": 76.515478,
      "entry_bo_score": 42.2,
      "entry_sm_label": "",
      "entry_sm_score": 0.0,
      "breakeven_price": 0.00052727,
      "entry_bo_signal": "PRIMED",
      "entry_mom_score": 26.4,
      "entry_price_ton": 0.0003429793002649272,
      "entry_mom_signal": "CALM",
      "entry_sm_buys_1h": 0,
      "entry_sm_sells_1h": 0
    },
    "updated_at": "2026-07-01T15:57:46.334819"
  },
  {
    "trade_id": "dedust_1782914151",
    "data": {
      "id": "dedust_1782914151",
      "pnl": 0.0,
      "side": "buy",
      "amount": 269400.470801,
      "status": "open",
      "symbol": "GRINCH/USDT",
      "entry_rsi": 0.0,
      "in_profit": false,
      "opened_at": "2026-07-01T13:55:51.505651",
      "stake_ton": 92.2284,
      "stop_loss": 0.0,
      "trail_pct": 7.0,
      "high_water": 0.0005502,
      "entry_price": 0.0005502,
      "net_pct_now": -16.59,
      "net_ton_now": -15.318041,
      "take_profit": 0.00061974,
      "entry_regime": "RANGING",
      "ai_confidence": 82.4,
      "entry_anomaly": false,
      "entry_atr_pct": 0.554,
      "min_gross_pct": 22.9,
      "value_ton_now": 78.046827,
      "entry_bo_score": 15.3,
      "entry_sm_label": "",
      "entry_sm_score": 0.0,
      "breakeven_price": 0.0005579,
      "entry_bo_signal": "FLAT",
      "entry_mom_score": 35.1,
      "entry_price_ton": 0.000341713661975473,
      "entry_mom_signal": "BUILDING",
      "entry_sm_buys_1h": 0,
      "entry_sm_sells_1h": 0
    },
    "updated_at": "2026-07-01T15:57:46.334819"
  },
  {
    "trade_id": "dedust_1782914260",
    "data": {
      "id": "dedust_1782914260",
      "pnl": 0.0,
      "side": "buy",
      "amount": 313695.421714,
      "status": "open",
      "symbol": "GRINCH/USDT",
      "entry_rsi": 0.0,
      "in_profit": false,
      "opened_at": "2026-07-01T13:57:40.816108",
      "stake_ton": 109.301,
      "stop_loss": 0.0,
      "trail_pct": 7.0,
      "high_water": 0.00053944,
      "entry_price": 0.00053944,
      "net_pct_now": -17.99,
      "net_ton_now": -19.686471,
      "take_profit": 0.00060728,
      "entry_regime": "SQUEEZE",
      "ai_confidence": 88.2,
      "entry_anomaly": false,
      "entry_atr_pct": 0.53,
      "min_gross_pct": 22.8,
      "value_ton_now": 90.879322,
      "entry_bo_score": 48.4,
      "entry_sm_label": "",
      "entry_sm_score": 0.0,
      "breakeven_price": 0.00054666,
      "entry_bo_signal": "PRIMED",
      "entry_mom_score": 30.3,
      "entry_price_ton": 0.0003423,
      "entry_mom_signal": "BUILDING",
      "entry_sm_buys_1h": 0,
      "entry_sm_sells_1h": 0
    },
    "updated_at": "2026-07-01T15:57:46.334819"
  },
  {
    "trade_id": "dedust_1782766735",
    "data": {
      "id": "dedust_1782766735",
      "pnl": 0.0,
      "side": "buy",
      "amount": 15448.789817,
      "status": "open",
      "symbol": "GRINCH/USDT",
      "entry_rsi": 0.0,
      "in_profit": false,
      "opened_at": "2026-06-29T20:58:55.831780",
      "stake_ton": 4.4982,
      "stop_loss": 0.0,
      "trail_pct": 7.0,
      "high_water": 0.00046485,
      "entry_price": 0.00046485,
      "net_pct_now": -9.2,
      "net_ton_now": -0.423355,
      "take_profit": 0.00060885,
      "entry_regime": "RANGING",
      "ai_confidence": 71.5,
      "entry_anomaly": false,
      "entry_atr_pct": 0.475,
      "min_gross_pct": 31.0,
      "value_ton_now": 4.475601,
      "entry_bo_score": 17.7,
      "entry_sm_label": "",
      "entry_sm_score": 0.0,
      "breakeven_price": 0.00050671,
      "entry_bo_signal": "FLAT",
      "entry_mom_score": 30.5,
      "entry_mom_signal": "BUILDING",
      "entry_sm_buys_1h": 0,
      "entry_sm_sells_1h": 0
    },
    "updated_at": "2026-07-01T15:57:46.334819"
  },
  {
    "trade_id": "dedust_1782903043",
    "data": {
      "id": "dedust_1782903043",
      "pnl": 0.0,
      "side": "buy",
      "amount": 15362.618693,
      "status": "open",
      "symbol": "GRINCH/USDT",
      "entry_rsi": 0.0,
      "in_profit": false,
      "opened_at": "2026-07-01T10:50:43.668197",
      "stake_ton": 4.6727,
      "stop_loss": 0.0,
      "trail_pct": 7.0,
      "high_water": 0.0004732,
      "entry_price": 0.0004732,
      "net_pct_now": -13.04,
      "net_ton_now": -0.62257,
      "take_profit": 0.00061828,
      "entry_regime": "SQUEEZE",
      "ai_confidence": 91.3,
      "entry_anomaly": false,
      "entry_atr_pct": 0.535,
      "min_gross_pct": 30.7,
      "value_ton_now": 4.450637,
      "entry_bo_score": 30.9,
      "entry_sm_label": "",
      "entry_sm_score": 0.0,
      "breakeven_price": 0.0005144,
      "entry_bo_signal": "COILING",
      "entry_mom_score": 32.4,
      "entry_price_ton": 0.0003012802871098823,
      "entry_mom_signal": "BUILDING",
      "entry_sm_buys_1h": 0,
      "entry_sm_sells_1h": 0
    },
    "updated_at": "2026-07-01T15:57:46.334819"
  }
]